CHANGELOG.txt
LICENSE
MANIFEST.in
README.md
setup.py
bnunicodenormalizer/__init__.py
bnunicodenormalizer/base.py
bnunicodenormalizer/indic.py
bnunicodenormalizer/langs.py
bnunicodenormalizer/normalizer.py
bnunicodenormalizer.egg-info/PKG-INFO
bnunicodenormalizer.egg-info/SOURCES.txt
bnunicodenormalizer.egg-info/dependency_links.txt
bnunicodenormalizer.egg-info/top_level.txt
extra/conjuncts.py
extra/missing.txt
tests/test_normalizer.py