Metadata-Version: 2.1
Name: bnunicodenormalizer
Version: 0.1.1
Summary: Bangla Unicode Normalization Toolkit
Home-page: https://github.com/mnansary/bnUnicodeNormalizer
Author: Bengali.AI
Author-email: research.bengaliai@gmail.com
License: MIT
Keywords: bangla,unicode,text normalization,indic
Platform: UNKNOWN
Classifier: Development Status :: 3 - Alpha
Classifier: Intended Audience :: Education
Classifier: Operating System :: OS Independent
Classifier: License :: OSI Approved :: MIT License
Classifier: Programming Language :: Python :: 3
License-File: LICENSE
